pond.py
pond-0.1.dist-info/licenses/LICENSE
pond-0.1.dist-info/WHEEL
pond-0.1.dist-info/METADATA
pond-0.1.dist-info/RECORD
