Metadata-Version: 2.4
Name: pond
Version: 0.1
Summary: pond
Author-email: Alec Edgington <alec.edgington@quantinuum.com>
License-Expression: Apache-2.0
License-File: LICENSE
